{
  "log_id": "LOG17739164674571",
  "timestamp": "2026-03-19T17:34:27.725682",
  "user": {
    "id": 8,
    "username": "user8",
    "name": "L\u00ea Th\u1ecb Mai",
    "email": "user8@gmail.com",
    "phone": "0310050771",
    "age": 45,
    "address": "369 L\u00ea L\u1ee3i, G\u00f2 V\u1ea5p",
    "district": "G\u00f2 V\u1ea5p",
    "balance": 1345,
    "membership_points": 0
  },
  "action": "checkout",
  "product": {
    "id": 10,
    "name": "Tr\u00e0 Cam Th\u1ea3o M\u1ed9c",
    "price": 49.0,
    "category": "drink",
    "stock_before": 58,
    "stock_after": 58
  },
  "quantity": 2,
  "status": "failed",
  "additional_data": {
    "payment_method": "Membership",
    "reason": "Ch\u1ec9 \u0111\u01b0\u1ee3c d\u00f9ng \u0111i\u1ec3m khi mua 1 s\u1ea3n ph\u1ea9m",
    "quantity": 2
  },
  "metadata": {
    "source": "log_generator",
    "version": "2.0",
    "user_segment": "regular"
  }
}