{
  "log_id": "LOG17750996986914",
  "timestamp": "2026-04-02T10:14:58.886186",
  "user": {
    "id": 17661,
    "username": "user17661",
    "name": "L\u00ea H\u1ed3ng An",
    "email": "user17661@gmail.com",
    "phone": "0496600221",
    "age": 37,
    "address": "406 L\u00ea L\u1ee3i, G\u00f2 V\u1ea5p",
    "district": "G\u00f2 V\u1ea5p",
    "balance": 4029,
    "membership_points": 6
  },
  "action": "checkout",
  "product": {
    "id": 5,
    "name": "G\u1ecfi C\u00e1 H\u1ed3i Chi\u00ean Gi\u00f2n",
    "price": 144.0,
    "category": "food",
    "stock_before": 54,
    "stock_after": 51
  },
  "quantity": 3,
  "status": "success",
  "additional_data": {
    "payment_method": "CurrentAccount",
    "balance_before": 4461,
    "balance_after": 4029,
    "points_earned": 3,
    "points_after": 6,
    "discount": 0,
    "subtotal": 432.0,
    "final_total": 432.0,
    "items": [
      {
        "product_id": 5,
        "product_name": "G\u1ecfi C\u00e1 H\u1ed3i Chi\u00ean Gi\u00f2n",
        "quantity": 3,
        "price": 144.0
      }
    ]
  },
  "metadata": {
    "source": "log_generator",
    "version": "2.0",
    "user_segment": "vip"
  }
}