{
  "log_id": "LOG17818803555021",
  "timestamp": "2026-06-19T21:45:55.337579",
  "user": {
    "id": 3057,
    "username": "user3057",
    "name": "Ho\u00e0ng H\u1ea3i H\u00e0",
    "email": "user3057@hotmail.com",
    "phone": "0367639063",
    "age": 62,
    "address": "376 Nguy\u1ec5n Hu\u1ec7, T\u00e2n Ph\u00fa",
    "district": "T\u00e2n Ph\u00fa",
    "balance": 1019,
    "membership_points": 7
  },
  "action": "login",
  "product": null,
  "quantity": null,
  "status": "success",
  "additional_data": {
    "login_method": "google",
    "session_id": "session_13785",
    "device": "mobile",
    "ip": "253.17.74.40"
  },
  "metadata": {
    "source": "log_generator",
    "version": "2.0",
    "user_segment": "regular"
  },
  "event_id": "LOG_1781880355341"
}